iretax/__init__.py
iretax/rebate_calculator.py
iretax/tax_calculator.py
iretax-0.0.3.dist-info/LICENSE
iretax-0.0.3.dist-info/METADATA
iretax-0.0.3.dist-info/WHEEL
iretax-0.0.3.dist-info/top_level.txt
iretax-0.0.3.dist-info/RECORD
