Metadata-Version: 2.1
Name: iretax
Version: 0.0.3
Summary: A Tax Calculation and Rebate System
Author-email: Shubham Goswami <goswamis@tcd.ie>
Project-URL: Homepage, https://github.com/ShubhZ33/iretax
Project-URL: Bug Tracker, https://github.com/ShubhZ33/iretax/issues
Classifier: Programming Language :: Python :: 3
Classifier: License :: OSI Approved :: MIT License
Classifier: Operating System :: OS Independent
Requires-Python: >=3.7
License-File: LICENSE
